teesign_utils/__init__.py
teesign_utils/azure_utils.py
teesign_utils/file_utils.py
tees_utils-0.1.dist-info/METADATA
tees_utils-0.1.dist-info/WHEEL
tees_utils-0.1.dist-info/top_level.txt
tees_utils-0.1.dist-info/RECORD
