Metadata-Version: 2.1
Name: tees-utils
Version: 0.1
Summary: A utility package for managing Teesign Utils.
Home-page: https://github.com/teesign/teesign-utils
Author: Divyansh
Author-email: divyansh.24888@gmail.com
Classifier: Programming Language :: Python :: 3
Classifier: License :: OSI Approved :: MIT License
Classifier: Operating System :: OS Independent
Requires-Python: >=3.9
Requires-Dist: azure-storage-blob
Requires-Dist: python-dotenv
Requires-Dist: requests
Requires-Dist: Pillow
Requires-Dist: pymongo
